mezzcaptcha
