Metadata-Version: 1.0
Name: mezzcaptcha
Version: 0.5
Summary: Custom mezzanine forms with captchas
Home-page: https://github.com/phookit/phookitmezz-captcha
Author: Paul Hunt
Author-email: paul@phookit.com
License: BSD
Platform: UNKNOWN
